{"stock": "NORD3", "date": "Jul 10, 2020", "open": 7.0, "high": 7.2, "low": 7.0, "close": 7.1, "volume": 1000.0, "volume medio": 224.86}
{"stock": "OMGE3", "date": "Jul 10, 2020", "open": 34.98, "high": 35.27, "low": 34.53, "close": 34.71, "volume": 125300.0, "volume medio": 159728.55}
{"stock": "SQIA3", "date": "Jul 10, 2020", "open": 23.61, "high": 23.88, "low": 23.25, "close": 23.86, "volume": 308700.0, "volume medio": 100042.64}
{"stock": "COGN3", "date": "Jul 10, 2020", "open": 7.9, "high": 8.47, "low": 7.85, "close": 8.4, "volume": 95177900.0, "volume medio": 2146398.13}
{"stock": "CAML3", "date": "Jul 10, 2020", "open": 11.45, "high": 11.49, "low": 11.3, "close": 11.41, "volume": 441200.0, "volume medio": 83076.68}
{"stock": "TUPY3", "date": "Jul 10, 2020", "open": 19.11, "high": 19.33, "low": 19.05, "close": 19.17, "volume": 323000.0, "volume medio": 83881.83}
{"stock": "BKBR3", "date": "Jul 10, 2020", "open": 11.42, "high": 12.19, "low": 11.26, "close": 12.17, "volume": 2433900.0, "volume medio": 129883.74}
{"stock": "BTOW3", "date": "Jul 10, 2020", "open": 119.79, "high": 121.36, "low": 117.53, "close": 120.27, "volume": 1278900.0, "volume medio": 1678471.7}
{"stock": "PRNR3", "date": "Jul 10, 2020", "open": 11.1, "high": 11.39, "low": 11.03, "close": 11.17, "volume": 181300.0, "volume medio": 17709.4}
{"stock": "APER3", "date": "Jul 10, 2020", "open": 34.35, "high": 34.78, "low": 33.69, "close": 34.01, "volume": 8100.0, "volume medio": 15436.73}
{"stock": "LPSB3", "date": "Jul 10, 2020", "open": 5.61, "high": 5.7, "low": 5.51, "close": 5.54, "volume": 469400.0, "volume medio": 37700.59}
{"stock": "BOBR4", "date": "Jul 10, 2020", "open": 2.4, "high": 2.4, "low": 2.28, "close": 2.35, "volume": 55400.0, "volume medio": 2831.9}
{"stock": "TELB3", "date": "Jul 10, 2020", "open": 159.0, "high": 163.0, "low": 158.5, "close": 163.0, "volume": 800.0, "volume medio": 1904.27}
{"stock": "ETER3", "date": "Jul 10, 2020", "open": 4.23, "high": 4.54, "low": 4.2, "close": 4.24, "volume": 1377100.0, "volume medio": 18471.4}
{"stock": "JBSS3", "date": "Jul 10, 2020", "open": 22.27, "high": 23.23, "low": 22.21, "close": 22.96, "volume": 13275200.0, "volume medio": 1879863.86}
{"stock": "TCNO3", "date": "Jul 10, 2020", "open": 2.83, "high": 3.09, "low": 2.83, "close": 2.97, "volume": 218400.0, "volume medio": 1490.94}
{"stock": "MOAR3", "date": "Jul 10, 2020", "open": 180.0, "high": 180.0, "low": 180.0, "close": 180.0, "volume": 100.0, "volume medio": 366.62}
{"stock": "MILS3", "date": "Jul 10, 2020", "open": 7.44, "high": 7.65, "low": 7.39, "close": 7.45, "volume": 964800.0, "volume medio": 89434.74}
{"stock": "RCSL4", "date": "Jul 10, 2020", "open": 2.22, "high": 2.32, "low": 2.22, "close": 2.31, "volume": 1421000.0, "volume medio": 32915.72}
{"stock": "ECOR3", "date": "Jul 10, 2020", "open": 14.36, "high": 14.44, "low": 14.03, "close": 14.13, "volume": 1704300.0, "volume medio": 350964.41}
{"stock": "ANIM3", "date": "Jul 10, 2020", "open": 25.17, "high": 25.45, "low": 24.88, "close": 25.37, "volume": 116400.0, "volume medio": 70923.14}
{"stock": "HBOR3", "date": "Jul 10, 2020", "open": 3.37, "high": 3.48, "low": 3.31, "close": 3.32, "volume": 21036200.0, "volume medio": 385412.37}
{"stock": "TCNO4", "date": "Jul 10, 2020", "open": 1.71, "high": 1.84, "low": 1.68, "close": 1.74, "volume": 513700.0, "volume medio": 1464.51}
{"stock": "USIM3", "date": "Jul 10, 2020", "open": 8.18, "high": 8.18, "low": 7.94, "close": 8.05, "volume": 73300.0, "volume medio": 12881.09}
{"stock": "USIM5", "date": "Jul 10, 2020", "open": 7.51, "high": 7.56, "low": 7.37, "close": 7.4, "volume": 9860200.0, "volume medio": 790992.98}
{"stock": "IGBR3", "date": "Jul 10, 2020", "open": 2.75, "high": 2.77, "low": 2.73, "close": 2.76, "volume": 9200.0, "volume medio": 1434.49}
{"stock": "PETR3", "date": "Jul 10, 2020", "open": 22.78, "high": 23.04, "low": 22.6, "close": 22.92, "volume": 3589500.0, "volume medio": 1684242.39}
{"stock": "PETR4", "date": "Jul 10, 2020", "open": 22.19, "high": 22.47, "low": 22.06, "close": 22.37, "volume": 28401300.0, "volume medio": 7347952.39}
{"stock": "RANI4", "date": "Jul 10, 2020", "open": 6.75, "high": 6.87, "low": 6.5, "close": 6.82, "volume": 5400.0, "volume medio": 540.83}
{"stock": "BIOM3", "date": "Jul 10, 2020", "open": 18.2, "high": 18.42, "low": 17.7, "close": 17.85, "volume": 32400.0, "volume medio": 12598.38}
{"stock": "VVAR3", "date": "Jul 10, 2020", "open": 17.65, "high": 18.06, "low": 17.5, "close": 17.74, "volume": 54588900.0, "volume medio": 6463931.46}
{"stock": "GBIO33", "date": "Jul 10, 2020", "open": 10.2, "high": 10.28, "low": 10.2, "close": 10.26, "volume": 2621000.0, "volume medio": 17628.27}
{"stock": "MEAL3", "date": "Jul 10, 2020", "open": 4.75, "high": 4.9, "low": 4.69, "close": 4.83, "volume": 7336600.0, "volume medio": 243390.68}
{"stock": "LOGN3", "date": "Jul 10, 2020", "open": 16.04, "high": 16.27, "low": 15.88, "close": 16.24, "volume": 308500.0, "volume medio": 85813.63}
{"stock": "RANI3", "date": "Jul 10, 2020", "open": 4.81, "high": 4.94, "low": 4.8, "close": 4.9, "volume": 16900.0, "volume medio": 1387.48}
{"stock": "CEDO3", "date": "Jul 10, 2020", "open": 11.8, "high": 12.1, "low": 11.8, "close": 12.1, "volume": 400.0, "volume medio": 414.03}
{"stock": "BAHI3", "date": "Jul 10, 2020", "open": 97.99, "high": 98.99, "low": 97.0, "close": 97.0, "volume": 800.0, "volume medio": 948.17}
{"stock": "AMAR3", "date": "Jul 10, 2020", "open": 8.69, "high": 8.92, "low": 8.66, "close": 8.76, "volume": 3138100.0, "volume medio": 317224.34}
{"stock": "KLBN3", "date": "Jul 10, 2020", "open": 4.24, "high": 4.24, "low": 4.16, "close": 4.19, "volume": 162000.0, "volume medio": 7797.09}
{"stock": "SPRI3", "date": "Jul 10, 2020", "open": 13.26, "high": 13.85, "low": 13.26, "close": 13.85, "volume": 300.0, "volume medio": 405.11}
{"stock": "KLBN4", "date": "Jul 10, 2020", "open": 4.11, "high": 4.12, "low": 4.04, "close": 4.08, "volume": 974300.0, "volume medio": 41968.52}
{"stock": "SPRI5", "date": "Jul 10, 2020", "open": 10.2, "high": 10.2, "low": 10.2, "close": 10.2, "volume": 200.0, "volume medio": 34.57}
{"stock": "CEDO4", "date": "Jul 10, 2020", "open": 6.81, "high": 6.81, "low": 6.81, "close": 6.81, "volume": 100.0, "volume medio": 496.93}
{"stock": "MDNE3", "date": "Jul 10, 2020", "open": 11.5, "high": 11.99, "low": 11.0, "close": 11.79, "volume": 542300.0, "volume medio": 24058.73}
{"stock": "DTCY3", "date": "Jul 10, 2020", "open": 6.25, "high": 6.4, "low": 5.87, "close": 6.0, "volume": 13500.0, "volume medio": 275.06}
{"stock": "ADHM3", "date": "Jul 10, 2020", "open": 2.46, "high": 2.46, "low": 2.45, "close": 2.46, "volume": 5300.0, "volume medio": 878.02}
{"stock": "PINE4", "date": "Jul 10, 2020", "open": 3.0, "high": 3.27, "low": 2.95, "close": 3.13, "volume": 1092500.0, "volume medio": 5400.62}
{"stock": "BSEV3", "date": "Jul 10, 2020", "open": 3.77, "high": 3.86, "low": 3.68, "close": 3.76, "volume": 50000.0, "volume medio": 3558.92}
{"stock": "MNDL3", "date": "Jul 10, 2020", "open": 24.5, "high": 24.5, "low": 24.5, "close": 24.5, "volume": 100.0, "volume medio": 1292.85}
{"stock": "TASA4", "date": "Jul 10, 2020", "open": 6.34, "high": 6.36, "low": 6.15, "close": 6.31, "volume": 498600.0, "volume medio": 56739.32}
{"stock": "TASA3", "date": "Jul 10, 2020", "open": 5.61, "high": 5.61, "low": 5.5, "close": 5.56, "volume": 53200.0, "volume medio": 5326.39}
{"stock": "JBDU3", "date": "Jul 10, 2020", "open": 3.23, "high": 3.47, "low": 3.23, "close": 3.38, "volume": 4000.0, "volume medio": 510.65}
{"stock": "SHOW3", "date": "Jul 10, 2020", "open": 2.88, "high": 3.15, "low": 2.85, "close": 3.09, "volume": 2740700.0, "volume medio": 18308.99}
{"stock": "SUZB3", "date": "Jul 10, 2020", "open": 36.47, "high": 36.89, "low": 36.27, "close": 36.83, "volume": 3247900.0, "volume medio": 1432443.32}
{"stock": "TESA3", "date": "Jul 10, 2020", "open": 17.45, "high": 17.67, "low": 17.18, "close": 17.67, "volume": 15300.0, "volume medio": 6405.86}
{"stock": "TCSA3", "date": "Jul 10, 2020", "open": 12.9, "high": 13.19, "low": 12.82, "close": 13.16, "volume": 1087500.0, "volume medio": 191879.74}
{"stock": "GOLL4", "date": "Jul 10, 2020", "open": 19.79, "high": 20.31, "low": 19.64, "close": 20.06, "volume": 5925500.0, "volume medio": 1759795.79}
{"stock": "BRKM3", "date": "Jul 10, 2020", "open": 25.04, "high": 25.07, "low": 24.5, "close": 24.5, "volume": 23000.0, "volume medio": 2955.06}
{"stock": "BRKM5", "date": "Jul 10, 2020", "open": 23.76, "high": 23.83, "low": 22.92, "close": 23.35, "volume": 2975600.0, "volume medio": 444372.35}
{"stock": "EMBR3", "date": "Jul 10, 2020", "open": 8.0, "high": 8.02, "low": 7.86, "close": 7.94, "volume": 5689400.0, "volume medio": 755864.42}
{"stock": "LLIS3", "date": "Jul 10, 2020", "open": 6.5, "high": 6.5, "low": 6.3, "close": 6.44, "volume": 107100.0, "volume medio": 15591.85}
{"stock": "GPIV33", "date": "Jul 10, 2020", "open": 5.05, "high": 5.05, "low": 4.81, "close": 4.96, "volume": 10500.0, "volume medio": 6041.86}
{"stock": "IDVL4", "date": "Jul 10, 2020", "open": 3.45, "high": 3.55, "low": 3.35, "close": 3.39, "volume": 12400.0, "volume medio": 257.59}
{"stock": "AZEV3", "date": "Jul 10, 2020", "open": 13.52, "high": 13.69, "low": 13.05, "close": 13.69, "volume": 3200.0, "volume medio": 4076.73}
{"stock": "MNPR3", "date": "Jul 10, 2020", "open": 5.28, "high": 5.36, "low": 5.17, "close": 5.25, "volume": 1600.0, "volume medio": 297.76}
{"stock": "JBDU4", "date": "Jul 10, 2020", "open": 1.61, "high": 1.72, "low": 1.61, "close": 1.69, "volume": 66600.0, "volume medio": 908.01}
{"stock": "IDVL3", "date": "Jul 10, 2020", "open": 2.71, "high": 2.87, "low": 2.7, "close": 2.74, "volume": 293700.0, "volume medio": 1606.35}
{"stock": "CTNM3", "date": "Jul 10, 2020", "open": 11.61, "high": 11.61, "low": 11.5, "close": 11.5, "volume": 1900.0, "volume medio": 517.28}
{"stock": "TPIS3", "date": "Jul 10, 2020", "open": 1.36, "high": 1.39, "low": 1.31, "close": 1.34, "volume": 823700.0, "volume medio": 6009.59}
{"stock": "RPMG3", "date": "Jul 10, 2020", "open": 2.99, "high": 2.99, "low": 2.91, "close": 2.93, "volume": 15400.0, "volume medio": 2487.07}
{"stock": "JFEN3", "date": "Jul 10, 2020", "open": 4.43, "high": 4.54, "low": 4.3, "close": 4.47, "volume": 18600.0, "volume medio": 3661.15}
{"stock": "PMAM3", "date": "Jul 10, 2020", "open": 13.84, "high": 14.42, "low": 13.83, "close": 14.14, "volume": 122400.0, "volume medio": 16730.43}
{"stock": "SGPS3", "date": "Jul 10, 2020", "open": 6.85, "high": 6.98, "low": 6.77, "close": 6.82, "volume": 134800.0, "volume medio": 7499.63}
{"stock": "LUPA3", "date": "Jul 10, 2020", "open": 2.66, "high": 2.69, "low": 2.48, "close": 2.5, "volume": 612700.0, "volume medio": 8613.86}
{"stock": "DMMO3", "date": "Jul 10, 2020", "open": 1.56, "high": 1.56, "low": 1.54, "close": 1.55, "volume": 1519300.0, "volume medio": 91364.05}
{"stock": "TECN3", "date": "Jul 10, 2020", "open": 1.44, "high": 1.58, "low": 1.42, "close": 1.5, "volume": 2287100.0, "volume medio": 4996.17}
{"stock": "AZUL4", "date": "Jul 10, 2020", "open": 20.75, "high": 21.24, "low": 20.63, "close": 20.93, "volume": 7314000.0, "volume medio": 2936208.46}
{"stock": "CTNM4", "date": "Jul 10, 2020", "open": 6.35, "high": 6.35, "low": 6.1, "close": 6.2, "volume": 19900.0, "volume medio": 1449.95}
{"stock": "AZEV4", "date": "Jul 10, 2020", "open": 4.62, "high": 4.78, "low": 4.61, "close": 4.68, "volume": 20500.0, "volume medio": 5806.89}
{"stock": "BBRK3", "date": "Jul 10, 2020", "open": 2.53, "high": 2.59, "low": 2.52, "close": 2.56, "volume": 237600.0, "volume medio": 16852.72}
{"stock": "OIBR4", "date": "Jul 10, 2020", "open": 1.47, "high": 1.49, "low": 1.44, "close": 1.49, "volume": 1767300.0, "volume medio": 22150.27}
{"stock": "VIVR3", "date": "Jul 10, 2020", "open": 1.93, "high": 1.99, "low": 1.9, "close": 1.91, "volume": 1680500.0, "volume medio": 16158.8}
{"stock": "OIBR3", "date": "Jul 10, 2020", "open": 1.13, "high": 1.18, "low": 1.08, "close": 1.17, "volume": 165575300.0, "volume medio": 1055602.92}
{"stock": "RSID3", "date": "Jul 10, 2020", "open": 6.41, "high": 6.47, "low": 6.31, "close": 6.38, "volume": 87100.0, "volume medio": 8408.11}
{"stock": "MGEL4", "date": "Jul 10, 2020", "open": 5.71, "high": 5.78, "low": 5.61, "close": 5.74, "volume": 2500.0, "volume medio": 316.33}
{"stock": "BDLL3", "date": "Jul 10, 2020", "open": 23.99, "high": 23.99, "low": 23.99, "close": 23.99, "volume": 1000.0, "volume medio": 114.24}
{"stock": "HOOT4", "date": "Jul 10, 2020", "open": 2.88, "high": 2.93, "low": 2.71, "close": 2.86, "volume": 5100.0, "volume medio": 165.13}
{"stock": "SLED3", "date": "Jul 10, 2020", "open": 1.8, "high": 1.82, "low": 1.75, "close": 1.77, "volume": 38400.0, "volume medio": 2676.86}
{"stock": "MWET4", "date": "Jul 10, 2020", "open": 3.95, "high": 4.15, "low": 3.81, "close": 4.05, "volume": 5500.0, "volume medio": 492.74}
{"stock": "RNEW3", "date": "Jul 10, 2020", "open": 3.65, "high": 3.65, "low": 3.55, "close": 3.55, "volume": 12500.0, "volume medio": 1241.24}
{"stock": "TEKA3", "date": "Jul 10, 2020", "open": 37.11, "high": 38.51, "low": 37.11, "close": 38.51, "volume": 800.0, "volume medio": 869.51}
{"stock": "RNEW4", "date": "Jul 10, 2020", "open": 3.15, "high": 3.2, "low": 3.12, "close": 3.17, "volume": 24900.0, "volume medio": 1574.43}
{"stock": "SLED4", "date": "Jul 10, 2020", "open": 0.93, "high": 0.94, "low": 0.92, "close": 0.93, "volume": 282800.0, "volume medio": 7189.51}
{"stock": "BDLL4", "date": "Jul 10, 2020", "open": 8.5, "high": 8.86, "low": 8.2, "close": 8.24, "volume": 1400.0, "volume medio": 145.96}
{"stock": "INEP3", "date": "Jul 10, 2020", "open": 6.8, "high": 6.94, "low": 6.65, "close": 6.65, "volume": 3300.0, "volume medio": 142.78}
{"stock": "INEP4", "date": "Jul 10, 2020", "open": 6.5, "high": 6.8, "low": 6.29, "close": 6.29, "volume": 900.0, "volume medio": 335.63}
{"stock": "MMXM3", "date": "Jul 10, 2020", "open": 1.96, "high": 1.96, "low": 1.89, "close": 1.93, "volume": 11200.0, "volume medio": 318.31}
{"stock": "PDGR3", "date": "Jul 10, 2020", "open": 5.5, "high": 5.53, "low": 5.35, "close": 5.5, "volume": 29600.0, "volume medio": 3622.96}
{"stock": "TEKA4", "date": "Jul 10, 2020", "open": 12.82, "high": 12.95, "low": 12.32, "close": 12.8, "volume": 4300.0, "volume medio": 2637.66}
{"stock": "OSXB3", "date": "Jul 10, 2020", "open": 4.63, "high": 4.63, "low": 4.52, "close": 4.55, "volume": 1300.0, "volume medio": 397.73}
{"stock": "ALPK3", "date": "Jul 10, 2020", "open": 9.82, "high": 9.82, "low": 9.6, "close": 9.62, "volume": 29600.0, "volume medio": 4994.11}
{"stock": "BBSE3", "date": "Jul 10, 2020", "open": 28.11, "high": 28.25, "low": 27.57, "close": 27.59, "volume": 3548100.0, "volume medio": 622748.32}
{"stock": "BMGB4", "date": "Jul 10, 2020", "open": 5.5, "high": 5.53, "low": 5.43, "close": 5.49, "volume": 655600.0, "volume medio": 35242.73}
{"stock": "IRBR3", "date": "Jul 10, 2020", "open": 9.35, "high": 9.42, "low": 9.12, "close": 9.17, "volume": 20753300.0, "volume medio": 3420522.42}
{"stock": "NTCO3", "date": "Jul 10, 2020", "open": 41.94, "high": 42.15, "low": 41.02, "close": 41.82, "volume": 2445800.0, "volume medio": 1419900.84}
{"stock": "TAEE3", "date": "Jul 10, 2020", "open": 9.58, "high": 9.58, "low": 9.49, "close": 9.5, "volume": 39100.0, "volume medio": 2567.42}
{"stock": "TAEE4", "date": "Jul 10, 2020", "open": 9.62, "high": 9.62, "low": 9.49, "close": 9.51, "volume": 69900.0, "volume medio": 4724.09}
{"stock": "VIVA3", "date": "Jul 10, 2020", "open": 22.24, "high": 22.25, "low": 21.81, "close": 21.98, "volume": 501100.0, "volume medio": 201872.74}
{"stock": "FHER3", "date": "Jul 10, 2020", "open": 3.33, "high": 3.33, "low": 3.2, "close": 3.29, "volume": 257100.0, "volume medio": 4769.79}
{"stock": "HETA4", "date": "Jul 10, 2020", "open": 8.96, "high": 9.02, "low": 8.75, "close": 8.75, "volume": 700.0, "volume medio": 521.15}
{"stock": "TXRX4", "date": "Jul 10, 2020", "open": 10.62, "high": 11.1, "low": 10.51, "close": 10.65, "volume": 4900.0, "volume medio": 5997.83}
{"stock": "PLAS3", "date": "Jul 10, 2020", "open": 5.15, "high": 5.15, "low": 4.95, "close": 4.95, "volume": 3300.0, "volume medio": 463.22}
{"stock": "CTKA4", "date": "Jul 10, 2020", "open": 12.43, "high": 12.49, "low": 11.4, "close": 11.76, "volume": 2700.0, "volume medio": 577.24}
{"stock": "SMLS3", "date": "Jul 10, 2020", "open": 14.82, "high": 15.13, "low": 14.7, "close": 14.99, "volume": 907400.0, "volume medio": 241795.07}
{"stock": "BAZA3", "date": "Jul 10, 2020", "open": 38.0, "high": 38.97, "low": 38.0, "close": 38.5, "volume": 1400.0, "volume medio": 734.09}
{"stock": "CEAB3", "date": "Jul 10, 2020", "open": 11.09, "high": 11.67, "low": 11.06, "close": 11.67, "volume": 2527300.0, "volume medio": 202772.77}
{"stock": "CGRA3", "date": "Jul 10, 2020", "open": 27.3, "high": 27.3, "low": 26.45, "close": 26.5, "volume": 1800.0, "volume medio": 247.39}
{"stock": "LIGT3", "date": "Jul 10, 2020", "open": 17.82, "high": 18.28, "low": 17.66, "close": 17.84, "volume": 831700.0, "volume medio": 239201.71}
{"stock": "BNBR3", "date": "Jul 10, 2020", "open": 81.51, "high": 84.99, "low": 81.51, "close": 84.99, "volume": 1000.0, "volume medio": 268.15}
{"stock": "CGRA4", "date": "Jul 10, 2020", "open": 26.5, "high": 26.8, "low": 25.76, "close": 25.98, "volume": 14200.0, "volume medio": 1171.46}
{"stock": "BRSR6", "date": "Jul 10, 2020", "open": 14.28, "high": 14.33, "low": 14.14, "close": 14.18, "volume": 968400.0, "volume medio": 212698.88}
{"stock": "BTTL3", "date": "Jul 10, 2020", "open": 6.43, "high": 6.43, "low": 6.43, "close": 6.43, "volume": 300.0, "volume medio": 113.95}
{"stock": "BRSR3", "date": "Jul 10, 2020", "open": 16.63, "high": 16.63, "low": 15.99, "close": 16.18, "volume": 51600.0, "volume medio": 5629.78}
{"stock": "BMEB4", "date": "Jul 10, 2020", "open": 14.69, "high": 14.69, "low": 14.59, "close": 14.59, "volume": 200.0, "volume medio": 630.19}
{"stock": "ELET3", "date": "Jul 10, 2020", "open": 36.11, "high": 37.34, "low": 35.2, "close": 35.95, "volume": 4939900.0, "volume medio": 806427.15}
{"stock": "ELET6", "date": "Jul 10, 2020", "open": 37.1, "high": 38.27, "low": 36.11, "close": 36.81, "volume": 2020200.0, "volume medio": 497682.43}
{"stock": "BBAS3", "date": "Jul 10, 2020", "open": 33.89, "high": 34.13, "low": 33.55, "close": 33.82, "volume": 8911700.0, "volume medio": 3357823.07}
{"stock": "EALT4", "date": "Jul 10, 2020", "open": 4.24, "high": 4.7, "low": 4.2, "close": 4.56, "volume": 130100.0, "volume medio": 1679.65}
{"stock": "BGIP4", "date": "Jul 10, 2020", "open": 32.5, "high": 32.5, "low": 32.01, "close": 32.01, "volume": 300.0, "volume medio": 568.55}
{"stock": "CRPG5", "date": "Jul 10, 2020", "open": 22.2, "high": 22.7, "low": 22.0, "close": 22.4, "volume": 8100.0, "volume medio": 979.92}
{"stock": "ABCB4", "date": "Jul 10, 2020", "open": 14.86, "high": 15.19, "low": 14.77, "close": 15.16, "volume": 369800.0, "volume medio": 70103.18}
{"stock": "CLSC4", "date": "Jul 10, 2020", "open": 60.0, "high": 61.0, "low": 59.6, "close": 59.99, "volume": 2100.0, "volume medio": 11741.81}
{"stock": "WHRL3", "date": "Jul 10, 2020", "open": 6.9, "high": 6.98, "low": 6.75, "close": 6.85, "volume": 10600.0, "volume medio": 940.85}
{"stock": "CESP6", "date": "Jul 10, 2020", "open": 28.9, "high": 29.16, "low": 28.87, "close": 29.05, "volume": 359200.0, "volume medio": 344669.62}
{"stock": "PRIO3", "date": "Jul 10, 2020", "open": 36.6, "high": 36.8, "low": 36.0, "close": 36.08, "volume": 1401000.0, "volume medio": 634175.12}
{"stock": "WHRL4", "date": "Jul 10, 2020", "open": 7.3, "high": 7.33, "low": 7.17, "close": 7.22, "volume": 11100.0, "volume medio": 2627.94}
{"stock": "BRSR5", "date": "Jul 10, 2020", "open": 21.5, "high": 21.5, "low": 21.5, "close": 21.5, "volume": 100.0, "volume medio": 129.15}
{"stock": "CMIG4", "date": "Jul 10, 2020", "open": 11.51, "high": 11.69, "low": 11.34, "close": 11.5, "volume": 3954400.0, "volume medio": 520619.6}
{"stock": "CRIV3", "date": "Jul 10, 2020", "open": 5.37, "high": 5.37, "low": 5.3, "close": 5.3, "volume": 400.0, "volume medio": 287.78}
{"stock": "GPCP3", "date": "Jul 10, 2020", "open": 40.0, "high": 43.99, "low": 40.0, "close": 43.49, "volume": 108600.0, "volume medio": 3609.91}
{"stock": "SANB3", "date": "Jul 10, 2020", "open": 14.39, "high": 14.45, "low": 14.08, "close": 14.17, "volume": 91800.0, "volume medio": 15577.22}
{"stock": "CMIG3", "date": "Jul 10, 2020", "open": 11.88, "high": 12.06, "low": 11.78, "close": 11.85, "volume": 383000.0, "volume medio": 107619.24}
{"stock": "SANB4", "date": "Jul 10, 2020", "open": 14.99, "high": 14.99, "low": 14.51, "close": 14.7, "volume": 100600.0, "volume medio": 14986.35}
{"stock": "CESP5", "date": "Jul 10, 2020", "open": 32.9, "high": 32.9, "low": 32.9, "close": 32.9, "volume": 5200.0, "volume medio": 318.27}
{"stock": "TRPL4", "date": "Jul 10, 2020", "open": 20.9, "high": 20.94, "low": 20.78, "close": 20.87, "volume": 380700.0, "volume medio": 182676.59}
{"stock": "MYPK3", "date": "Jul 10, 2020", "open": 14.1, "high": 14.2, "low": 13.76, "close": 13.82, "volume": 2150000.0, "volume medio": 146809.49}
{"stock": "BRML3", "date": "Jul 10, 2020", "open": 10.99, "high": 11.32, "low": 10.96, "close": 11.25, "volume": 5373000.0, "volume medio": 707404.66}
{"stock": "CESP3", "date": "Jul 10, 2020", "open": 33.76, "high": 33.76, "low": 33.05, "close": 33.27, "volume": 1500.0, "volume medio": 2076.55}
{"stock": "CEBR3", "date": "Jul 10, 2020", "open": 58.0, "high": 58.45, "low": 58.0, "close": 58.45, "volume": 300.0, "volume medio": 1202.91}
{"stock": "BEES3", "date": "Jul 10, 2020", "open": 5.99, "high": 6.0, "low": 5.97, "close": 6.0, "volume": 23100.0, "volume medio": 840.35}
{"stock": "CPLE3", "date": "Jul 10, 2020", "open": 59.56, "high": 59.58, "low": 58.41, "close": 58.72, "volume": 126700.0, "volume medio": 99910.48}
{"stock": "ENBR3", "date": "Jul 10, 2020", "open": 17.78, "high": 17.83, "low": 17.61, "close": 17.64, "volume": 818900.0, "volume medio": 195653.38}
{"stock": "WIZS3", "date": "Jul 10, 2020", "open": 10.68, "high": 10.95, "low": 10.59, "close": 10.86, "volume": 555200.0, "volume medio": 53012.55}
{"stock": "BEES4", "date": "Jul 10, 2020", "open": 6.17, "high": 6.19, "low": 6.15, "close": 6.15, "volume": 2300.0, "volume medio": 212.15}
{"stock": "SAPR4", "date": "Jul 10, 2020", "open": 6.21, "high": 6.26, "low": 6.18, "close": 6.23, "volume": 768500.0, "volume medio": 94726.87}
{"stock": "CAMB3", "date": "Jul 10, 2020", "open": 4.81, "high": 4.81, "low": 4.62, "close": 4.65, "volume": 190900.0, "volume medio": 12822.13}
{"stock": "CPLE6", "date": "Jul 10, 2020", "open": 61.1, "high": 61.58, "low": 60.55, "close": 60.94, "volume": 373200.0, "volume medio": 334743.63}
{"stock": "CRIV4", "date": "Jul 10, 2020", "open": 6.47, "high": 6.49, "low": 6.47, "close": 6.48, "volume": 2900.0, "volume medio": 100.73}
{"stock": "ATOM3", "date": "Jul 10, 2020", "open": 2.25, "high": 2.25, "low": 2.12, "close": 2.16, "volume": 149200.0, "volume medio": 1558.09}
{"stock": "SAPR3", "date": "Jul 10, 2020", "open": 6.66, "high": 6.66, "low": 6.55, "close": 6.63, "volume": 71000.0, "volume medio": 9713.29}
{"stock": "BBDC3", "date": "Jul 10, 2020", "open": 20.28, "high": 20.49, "low": 20.01, "close": 20.21, "volume": 1564600.0, "volume medio": 594516.56}
{"stock": "COCE5", "date": "Jul 10, 2020", "open": 56.61, "high": 56.86, "low": 56.0, "close": 56.77, "volume": 3300.0, "volume medio": 6352.93}
{"stock": "TGMA3", "date": "Jul 10, 2020", "open": 25.82, "high": 25.91, "low": 25.15, "close": 25.48, "volume": 172800.0, "volume medio": 84579.11}
{"stock": "TRPL3", "date": "Jul 10, 2020", "open": 25.0, "high": 25.29, "low": 24.8, "close": 25.29, "volume": 3400.0, "volume medio": 548.06}
{"stock": "EQTL3", "date": "Jul 10, 2020", "open": 24.12, "high": 24.39, "low": 23.82, "close": 24.29, "volume": 1745600.0, "volume medio": 813538.82}
{"stock": "BRGE12", "date": "Jul 10, 2020", "open": 5.9, "high": 6.2, "low": 5.9, "close": 6.2, "volume": 1200.0, "volume medio": 44.13}
{"stock": "BRPR3", "date": "Jul 10, 2020", "open": 9.57, "high": 10.06, "low": 9.52, "close": 9.99, "volume": 6101100.0, "volume medio": 154711.53}
{"stock": "HAGA4", "date": "Jul 10, 2020", "open": 2.14, "high": 2.18, "low": 2.06, "close": 2.09, "volume": 173200.0, "volume medio": 5058.26}
{"stock": "ALUP4", "date": "Jul 10, 2020", "open": 7.25, "high": 7.25, "low": 7.17, "close": 7.18, "volume": 16800.0, "volume medio": 906.1}
{"stock": "FESA4", "date": "Jul 10, 2020", "open": 18.45, "high": 18.63, "low": 18.07, "close": 18.6, "volume": 150000.0, "volume medio": 37760.12}
{"stock": "ITSA4", "date": "Jul 10, 2020", "open": 10.15, "high": 10.26, "low": 10.07, "close": 10.15, "volume": 10197300.0, "volume medio": 1540869.96}
{"stock": "EUCA4", "date": "Jul 10, 2020", "open": 6.56, "high": 6.65, "low": 6.47, "close": 6.51, "volume": 44500.0, "volume medio": 4737.26}
{"stock": "BBDC4", "date": "Jul 10, 2020", "open": 21.94, "high": 22.25, "low": 21.65, "close": 21.88, "volume": 48404600.0, "volume medio": 5476320.6}
{"stock": "TIMP3", "date": "Jul 10, 2020", "open": 14.8, "high": 14.82, "low": 14.53, "close": 14.72, "volume": 3887000.0, "volume medio": 585182.58}
{"stock": "PTNT4", "date": "Jul 10, 2020", "open": 4.7, "high": 4.98, "low": 4.7, "close": 4.81, "volume": 32700.0, "volume medio": 1435.56}
{"stock": "CSMG3", "date": "Jul 10, 2020", "open": 58.1, "high": 58.1, "low": 57.23, "close": 57.91, "volume": 211100.0, "volume medio": 265886.43}
{"stock": "NEOE3", "date": "Jul 10, 2020", "open": 19.83, "high": 19.99, "low": 19.5, "close": 19.82, "volume": 622200.0, "volume medio": 237558.01}
{"stock": "NEOE3", "date": "Jul 10, 2020", "open": 19.83, "high": 19.99, "low": 19.5, "close": 19.82, "volume": 622200.0, "volume medio": 237558.01}
{"stock": "ROMI3", "date": "Jul 10, 2020", "open": 13.91, "high": 14.08, "low": 13.61, "close": 13.81, "volume": 134800.0, "volume medio": 18582.36}
{"stock": "VULC3", "date": "Jul 10, 2020", "open": 5.46, "high": 5.57, "low": 5.42, "close": 5.51, "volume": 496600.0, "volume medio": 29985.44}
{"stock": "ITSA3", "date": "Jul 10, 2020", "open": 11.61, "high": 11.61, "low": 11.48, "close": 11.52, "volume": 90800.0, "volume medio": 13384.52}
{"stock": "BRIV4", "date": "Jul 10, 2020", "open": 7.5, "high": 7.5, "low": 7.5, "close": 7.5, "volume": 100.0, "volume medio": 232.12}
{"stock": "BRIV3", "date": "Jul 10, 2020", "open": 7.53, "high": 7.53, "low": 7.53, "close": 7.53, "volume": 100.0, "volume medio": 37.97}
{"stock": "ITUB3", "date": "Jul 10, 2020", "open": 25.13, "high": 25.29, "low": 24.75, "close": 24.95, "volume": 332700.0, "volume medio": 135141.77}
{"stock": "CIEL3", "date": "Jul 10, 2020", "open": 5.03, "high": 5.13, "low": 4.79, "close": 4.82, "volume": 49467900.0, "volume medio": 1395483.24}
{"stock": "LEVE3", "date": "Jul 10, 2020", "open": 19.09, "high": 19.09, "low": 18.73, "close": 18.81, "volume": 180900.0, "volume medio": 46727.55}
{"stock": "SHUL4", "date": "Jul 10, 2020", "open": 12.33, "high": 12.51, "low": 12.16, "close": 12.3, "volume": 150100.0, "volume medio": 14287.41}
{"stock": "SMTO3", "date": "Jul 10, 2020", "open": 20.49, "high": 20.66, "low": 20.31, "close": 20.4, "volume": 611000.0, "volume medio": 168030.7}
{"stock": "CVCB3", "date": "Jul 10, 2020", "open": 19.3, "high": 21.07, "low": 19.11, "close": 21.08, "volume": 13226200.0, "volume medio": 763597.87}
{"stock": "CPFE3", "date": "Jul 10, 2020", "open": 30.2, "high": 30.4, "low": 30.06, "close": 30.09, "volume": 733000.0, "volume medio": 494607.57}
{"stock": "ITUB4", "date": "Jul 10, 2020", "open": 26.95, "high": 27.25, "low": 26.62, "close": 26.93, "volume": 14172000.0, "volume medio": 5495500.72}
{"stock": "ENAT3", "date": "Jul 10, 2020", "open": 10.95, "high": 10.98, "low": 10.68, "close": 10.75, "volume": 670900.0, "volume medio": 116424.85}
{"stock": "MTSA4", "date": "Jul 10, 2020", "open": 17.8, "high": 17.8, "low": 17.8, "close": 17.8, "volume": 400.0, "volume medio": 794.56}
{"stock": "WLMM4", "date": "Jul 10, 2020", "open": 17.36, "high": 17.96, "low": 17.36, "close": 17.96, "volume": 800.0, "volume medio": 171.99}
{"stock": "ALUP3", "date": "Jul 10, 2020", "open": 9.7, "high": 9.74, "low": 9.65, "close": 9.65, "volume": 2800.0, "volume medio": 977.41}
{"stock": "PSSA3", "date": "Jul 10, 2020", "open": 53.59, "high": 53.73, "low": 52.73, "close": 53.03, "volume": 227500.0, "volume medio": 192100.3}
{"stock": "SLCE3", "date": "Jul 10, 2020", "open": 24.54, "high": 24.98, "low": 24.48, "close": 24.8, "volume": 1001200.0, "volume medio": 179294.38}
{"stock": "LUXM4", "date": "Jul 10, 2020", "open": 33.0, "high": 33.0, "low": 33.0, "close": 33.0, "volume": 200.0, "volume medio": 125.46}
{"stock": "BRFS3", "date": "Jul 10, 2020", "open": 20.67, "high": 20.76, "low": 20.47, "close": 20.69, "volume": 4125100.0, "volume medio": 980661.52}
{"stock": "BRDT3", "date": "Jul 10, 2020", "open": 22.8, "high": 23.01, "low": 22.46, "close": 22.53, "volume": 1888300.0, "volume medio": 943319.63}
{"stock": "EMAE4", "date": "Jul 10, 2020", "open": 29.49, "high": 30.09, "low": 29.49, "close": 29.66, "volume": 3700.0, "volume medio": 931.3}
{"stock": "RAPT3", "date": "Jul 10, 2020", "open": 8.88, "high": 8.89, "low": 8.81, "close": 8.86, "volume": 4000.0, "volume medio": 808.97}
{"stock": "DOHL4", "date": "Jul 10, 2020", "open": 5.98, "high": 6.26, "low": 5.98, "close": 6.26, "volume": 1500.0, "volume medio": 176.62}
{"stock": "BRGE3", "date": "Jul 10, 2020", "open": 9.01, "high": 9.01, "low": 9.01, "close": 9.01, "volume": 500.0, "volume medio": 76.62}
{"stock": "POMO3", "date": "Jul 10, 2020", "open": 2.83, "high": 2.84, "low": 2.8, "close": 2.82, "volume": 172500.0, "volume medio": 8126.46}
{"stock": "HGTX3", "date": "Jul 10, 2020", "open": 15.15, "high": 16.35, "low": 15.15, "close": 16.25, "volume": 4267400.0, "volume medio": 274112.17}
{"stock": "GEPA4", "date": "Jul 10, 2020", "open": 45.5, "high": 46.5, "low": 45.5, "close": 45.54, "volume": 400.0, "volume medio": 107.66}
{"stock": "POMO4", "date": "Jul 10, 2020", "open": 3.02, "high": 3.02, "low": 2.97, "close": 2.98, "volume": 5065300.0, "volume medio": 229466.88}
{"stock": "FRTA3", "date": "Jul 10, 2020", "open": 4.92, "high": 5.05, "low": 4.92, "close": 5.05, "volume": 2600.0, "volume medio": 263.38}
{"stock": "EQPA3", "date": "Jul 10, 2020", "open": 3.6, "high": 3.61, "low": 3.54, "close": 3.58, "volume": 11900.0, "volume medio": 1840.01}
{"stock": "PTBL3", "date": "Jul 10, 2020", "open": 4.74, "high": 4.78, "low": 4.64, "close": 4.69, "volume": 659400.0, "volume medio": 44118.51}
{"stock": "SULA4", "date": "Jul 10, 2020", "open": 13.35, "high": 13.51, "low": 13.16, "close": 13.46, "volume": 1800.0, "volume medio": 842.29}
{"stock": "CGAS5", "date": "Jul 10, 2020", "open": 178.78, "high": 178.78, "low": 175.35, "close": 176.0, "volume": 5600.0, "volume medio": 4507.47}
{"stock": "TEND3", "date": "Jul 10, 2020", "open": 33.59, "high": 35.05, "low": 33.59, "close": 34.97, "volume": 448200.0, "volume medio": 208367.08}
{"stock": "PTNT3", "date": "Jul 10, 2020", "open": 7.04, "high": 7.19, "low": 7.04, "close": 7.2, "volume": 2000.0, "volume medio": 581.26}
{"stock": "EGIE3", "date": "Jul 10, 2020", "open": 43.27, "high": 43.67, "low": 42.95, "close": 42.98, "volume": 2524200.0, "volume medio": 427982.91}
{"stock": "GRND3", "date": "Jul 10, 2020", "open": 7.87, "high": 7.87, "low": 7.76, "close": 7.8, "volume": 576600.0, "volume medio": 63341.83}
{"stock": "MRVE3", "date": "Jul 10, 2020", "open": 20.25, "high": 21.27, "low": 20.17, "close": 21.17, "volume": 4653700.0, "volume medio": 430540.57}
{"stock": "RPAD5", "date": "Jul 10, 2020", "open": 8.25, "high": 8.25, "low": 8.2, "close": 8.2, "volume": 1000.0, "volume medio": 55.37}
{"stock": "GUAR3", "date": "Jul 10, 2020", "open": 17.35, "high": 17.85, "low": 17.22, "close": 17.84, "volume": 902400.0, "volume medio": 139309.26}
{"stock": "VIVT3", "date": "Jul 10, 2020", "open": 49.76, "high": 49.8, "low": 48.72, "close": 48.77, "volume": 50000.0, "volume medio": 21698.99}
{"stock": "VIVT4", "date": "Jul 10, 2020", "open": 49.69, "high": 49.76, "low": 48.82, "close": 48.85, "volume": 675400.0, "volume medio": 661235.61}
{"stock": "CARD3", "date": "Jul 10, 2020", "open": 13.08, "high": 13.08, "low": 12.86, "close": 12.89, "volume": 81400.0, "volume medio": 20712.33}
{"stock": "RAPT4", "date": "Jul 10, 2020", "open": 11.06, "high": 11.26, "low": 10.85, "close": 11.2, "volume": 2717900.0, "volume medio": 219650.43}
{"stock": "TRIS3", "date": "Jul 10, 2020", "open": 13.5, "high": 14.19, "low": 13.46, "close": 14.16, "volume": 1725900.0, "volume medio": 136771.24}
{"stock": "HAGA3", "date": "Jul 10, 2020", "open": 3.63, "high": 3.82, "low": 3.63, "close": 3.7, "volume": 22100.0, "volume medio": 1076.43}
{"stock": "ENGI4", "date": "Jul 10, 2020", "open": 8.89, "high": 8.94, "low": 8.73, "close": 8.78, "volume": 14400.0, "volume medio": 837.64}
{"stock": "JHSF3", "date": "Jul 10, 2020", "open": 9.41, "high": 9.64, "low": 9.35, "close": 9.54, "volume": 5389000.0, "volume medio": 516388.33}
{"stock": "YDUQ3", "date": "Jul 10, 2020", "open": 34.55, "high": 36.0, "low": 34.41, "close": 35.32, "volume": 2544600.0, "volume medio": 654369.11}
{"stock": "EALT3", "date": "Jul 10, 2020", "open": 12.81, "high": 14.0, "low": 12.81, "close": 13.02, "volume": 2400.0, "volume medio": 528.58}
{"stock": "VLID3", "date": "Jul 10, 2020", "open": 11.13, "high": 11.26, "low": 10.94, "close": 11.09, "volume": 391100.0, "volume medio": 57913.27}
{"stock": "HYPE3", "date": "Jul 10, 2020", "open": 32.2, "high": 32.66, "low": 32.11, "close": 32.52, "volume": 2038200.0, "volume medio": 577468.4}
{"stock": "BPAN4", "date": "Jul 10, 2020", "open": 9.31, "high": 9.36, "low": 9.19, "close": 9.3, "volume": 1636300.0, "volume medio": 290663.7}
{"stock": "SBSP3", "date": "Jul 10, 2020", "open": 57.6, "high": 58.65, "low": 57.3, "close": 57.96, "volume": 2143200.0, "volume medio": 1158690.99}
{"stock": "TIET4", "date": "Jul 10, 2020", "open": 3.17, "high": 3.23, "low": 3.17, "close": 3.19, "volume": 228700.0, "volume medio": 10695.41}
{"stock": "PARD3", "date": "Jul 10, 2020", "open": 22.0, "high": 22.16, "low": 21.6, "close": 22.12, "volume": 197000.0, "volume medio": 51869.71}
{"stock": "SEER3", "date": "Jul 10, 2020", "open": 15.1, "high": 15.52, "low": 14.85, "close": 15.5, "volume": 565300.0, "volume medio": 83999.09}
{"stock": "JOPA4", "date": "Jul 10, 2020", "open": 28.0, "high": 28.0, "low": 28.0, "close": 28.0, "volume": 100.0, "volume medio": 96.61}
{"stock": "JPSA3", "date": "Jul 10, 2020", "open": 25.3, "high": 25.47, "low": 25.0, "close": 25.36, "volume": 130000.0, "volume medio": 41673.51}
{"stock": "BEEF3", "date": "Jul 10, 2020", "open": 13.26, "high": 13.53, "low": 13.16, "close": 13.46, "volume": 1993000.0, "volume medio": 511449.05}
{"stock": "GOAU3", "date": "Jul 10, 2020", "open": 6.76, "high": 6.8, "low": 6.7, "close": 6.72, "volume": 65300.0, "volume medio": 4276.57}
{"stock": "UCAS3", "date": "Jul 10, 2020", "open": 4.65, "high": 4.79, "low": 4.56, "close": 4.59, "volume": 104600.0, "volume medio": 3690.95}
{"stock": "TIET3", "date": "Jul 10, 2020", "open": 3.4, "high": 3.45, "low": 3.4, "close": 3.42, "volume": 73700.0, "volume medio": 3030.72}
{"stock": "MDIA3", "date": "Jul 10, 2020", "open": 40.92, "high": 41.12, "low": 40.22, "close": 40.46, "volume": 355400.0, "volume medio": 179576.19}
{"stock": "MERC4", "date": "Jul 10, 2020", "open": 12.5, "high": 12.5, "low": 12.5, "close": 12.5, "volume": 300.0, "volume medio": 803.56}
{"stock": "CCRO3", "date": "Jul 10, 2020", "open": 14.53, "high": 14.63, "low": 14.03, "close": 14.42, "volume": 5873900.0, "volume medio": 648684.71}
{"stock": "ABEV3", "date": "Jul 10, 2020", "open": 14.62, "high": 14.99, "low": 14.55, "close": 14.81, "volume": 11120400.0, "volume medio": 1749670.82}
{"stock": "GOAU4", "date": "Jul 10, 2020", "open": 7.3, "high": 7.4, "low": 7.26, "close": 7.38, "volume": 5148300.0, "volume medio": 537131.78}
{"stock": "IGTA3", "date": "Jul 10, 2020", "open": 36.17, "high": 36.65, "low": 35.64, "close": 36.47, "volume": 804800.0, "volume medio": 434619.97}
{"stock": "ENEV3", "date": "Jul 10, 2020", "open": 48.06, "high": 48.36, "low": 47.7, "close": 47.92, "volume": 292300.0, "volume medio": 374761.92}
{"stock": "SULA3", "date": "Jul 10, 2020", "open": 20.31, "high": 20.69, "low": 20.31, "close": 20.54, "volume": 1700.0, "volume medio": 697.62}
{"stock": "CTSA4", "date": "Jul 10, 2020", "open": 3.11, "high": 3.18, "low": 3.05, "close": 3.1, "volume": 22400.0, "volume medio": 625.49}
{"stock": "QUAL3", "date": "Jul 10, 2020", "open": 30.42, "high": 30.44, "low": 29.96, "close": 30.09, "volume": 725200.0, "volume medio": 511430.82}
{"stock": "ENGI3", "date": "Jul 10, 2020", "open": 12.2, "high": 12.21, "low": 12.01, "close": 12.14, "volume": 4400.0, "volume medio": 516.58}
{"stock": "GGBR3", "date": "Jul 10, 2020", "open": 13.83, "high": 13.83, "low": 13.61, "close": 13.68, "volume": 80300.0, "volume medio": 10590.26}
{"stock": "SCAR3", "date": "Jul 10, 2020", "open": 38.34, "high": 39.95, "low": 38.15, "close": 39.56, "volume": 7100.0, "volume medio": 2584.65}
{"stock": "KEPL3", "date": "Jul 10, 2020", "open": 39.3, "high": 39.5, "low": 38.95, "close": 39.2, "volume": 34600.0, "volume medio": 21659.29}
{"stock": "MULT3", "date": "Jul 10, 2020", "open": 23.3, "high": 23.72, "low": 22.96, "close": 23.59, "volume": 2974300.0, "volume medio": 725211.29}
{"stock": "CNTO3", "date": "Jul 10, 2020", "open": 33.92, "high": 34.6, "low": 33.27, "close": 33.64, "volume": 1162800.0, "volume medio": 398295.25}
{"stock": "DTEX3", "date": "Jul 10, 2020", "open": 15.56, "high": 15.63, "low": 15.23, "close": 15.58, "volume": 1475000.0, "volume medio": 250599.22}
{"stock": "EQPA7", "date": "Jul 10, 2020", "open": 6.0, "high": 6.0, "low": 6.0, "close": 6.0, "volume": 100.0, "volume medio": 99.9}
{"stock": "EVEN3", "date": "Jul 10, 2020", "open": 13.09, "high": 13.35, "low": 12.7, "close": 13.31, "volume": 2197300.0, "volume medio": 187981.34}
{"stock": "LCAM3", "date": "Jul 10, 2020", "open": 18.04, "high": 18.15, "low": 17.75, "close": 18.08, "volume": 761200.0, "volume medio": 284240.08}
{"stock": "BPAC5", "date": "Jul 10, 2020", "open": 23.9, "high": 23.9, "low": 23.89, "close": 23.9, "volume": 400.0, "volume medio": 305.66}
{"stock": "CYRE3", "date": "Jul 10, 2020", "open": 26.73, "high": 27.98, "low": 26.61, "close": 27.59, "volume": 7566300.0, "volume medio": 983630.57}
{"stock": "CTSA3", "date": "Jul 10, 2020", "open": 3.5, "high": 3.65, "low": 3.4, "close": 3.45, "volume": 34500.0, "volume medio": 1278.21}
{"stock": "FRAS3", "date": "Jul 10, 2020", "open": 5.59, "high": 5.59, "low": 5.42, "close": 5.48, "volume": 48200.0, "volume medio": 3595.58}
{"stock": "EZTC3", "date": "Jul 10, 2020", "open": 42.4, "high": 42.45, "low": 41.54, "close": 42.29, "volume": 1594600.0, "volume medio": 564128.55}
{"stock": "GGBR4", "date": "Jul 10, 2020", "open": 16.05, "high": 16.22, "low": 15.94, "close": 16.1, "volume": 8360400.0, "volume medio": 1285214.45}
{"stock": "AFLT3", "date": "Jul 10, 2020", "open": 11.4, "high": 11.4, "low": 10.8, "close": 11.08, "volume": 7000.0, "volume medio": 509.18}
{"stock": "ARZZ3", "date": "Jul 10, 2020", "open": 51.5, "high": 52.23, "low": 51.08, "close": 51.67, "volume": 349000.0, "volume medio": 152494.63}
{"stock": "DIRR3", "date": "Jul 10, 2020", "open": 17.64, "high": 17.89, "low": 17.47, "close": 17.65, "volume": 567100.0, "volume medio": 112355.82}
{"stock": "FLRY3", "date": "Jul 10, 2020", "open": 25.6, "high": 25.84, "low": 25.4, "close": 25.47, "volume": 763600.0, "volume medio": 268241.69}
{"stock": "ODPV3", "date": "Jul 10, 2020", "open": 15.0, "high": 15.05, "low": 14.57, "close": 14.6, "volume": 908400.0, "volume medio": 108241.0}
{"stock": "POSI3", "date": "Jul 10, 2020", "open": 5.45, "high": 5.59, "low": 5.42, "close": 5.57, "volume": 2524600.0, "volume medio": 167282.28}
{"stock": "BMIN4", "date": "Jul 10, 2020", "open": 19.5, "high": 20.0, "low": 19.5, "close": 20.0, "volume": 500.0, "volume medio": 220.91}
{"stock": "AGRO3", "date": "Jul 10, 2020", "open": 22.27, "high": 23.29, "low": 22.22, "close": 22.73, "volume": 272400.0, "volume medio": 17488.66}
{"stock": "BMKS3", "date": "Jul 10, 2020", "open": 186.0, "high": 194.5, "low": 186.0, "close": 194.49, "volume": 168.0, "volume medio": 105.14}
{"stock": "CSAN3", "date": "Jul 10, 2020", "open": 73.88, "high": 75.21, "low": 73.88, "close": 74.83, "volume": 1111400.0, "volume medio": 598078.58}
{"stock": "OFSA3", "date": "Jul 10, 2020", "open": 31.24, "high": 32.67, "low": 31.24, "close": 32.5, "volume": 28500.0, "volume medio": 3652.19}
{"stock": "BMIN3", "date": "Jul 10, 2020", "open": 0.0, "high": 21.51, "low": 20.5, "close": 21.0, "volume": 1700.0, "volume medio": 268.12}
{"stock": "CSNA3", "date": "Jul 10, 2020", "open": 11.1, "high": 11.23, "low": 11.05, "close": 11.18, "volume": 3783900.0, "volume medio": 624796.61}
{"stock": "REDE3", "date": "Jul 10, 2020", "open": 0.0, "high": 10.3, "low": 10.01, "close": 10.3, "volume": 900.0, "volume medio": 61.05}
{"stock": "LREN3", "date": "Jul 10, 2020", "open": 44.0, "high": 44.95, "low": 43.76, "close": 44.4, "volume": 2205200.0, "volume medio": 1604060.31}
{"stock": "PFRM3", "date": "Jul 10, 2020", "open": 6.59, "high": 6.73, "low": 6.46, "close": 6.67, "volume": 445600.0, "volume medio": 26221.34}
{"stock": "LOGG3", "date": "Jul 10, 2020", "open": 34.9, "high": 35.34, "low": 34.59, "close": 34.85, "volume": 112300.0, "volume medio": 74042.91}
{"stock": "EUCA3", "date": "Jul 10, 2020", "open": 26.7, "high": 26.7, "low": 26.5, "close": 26.5, "volume": 2000.0, "volume medio": 4258.32}
{"stock": "PCAR3", "date": "Jul 10, 2020", "open": 71.99, "high": 71.99, "low": 70.36, "close": 70.69, "volume": 393600.0, "volume medio": 529765.98}
{"stock": "RENT3", "date": "Jul 10, 2020", "open": 42.88, "high": 43.6, "low": 42.74, "close": 43.6, "volume": 1837800.0, "volume medio": 1375828.71}
{"stock": "B3SA3", "date": "Jul 10, 2020", "open": 58.8, "high": 59.61, "low": 57.6, "close": 59.33, "volume": 5470900.0, "volume medio": 2781945.89}
{"stock": "JSLG3", "date": "Jul 10, 2020", "open": 27.75, "high": 28.0, "low": 27.12, "close": 27.36, "volume": 387100.0, "volume medio": 166436.06}
{"stock": "CRFB3", "date": "Jul 10, 2020", "open": 20.2, "high": 20.27, "low": 19.76, "close": 20.15, "volume": 1775900.0, "volume medio": 474734.5}
{"stock": "BPAC3", "date": "Jul 10, 2020", "open": 39.0, "high": 39.0, "low": 37.56, "close": 39.0, "volume": 1700.0, "volume medio": 471.26}
{"stock": "PNVL4", "date": "Jul 10, 2020", "open": 25.13, "high": 25.69, "low": 25.01, "close": 25.29, "volume": 8200.0, "volume medio": 3103.14}
{"stock": "RADL3", "date": "Jul 10, 2020", "open": 112.48, "high": 113.55, "low": 110.39, "close": 110.62, "volume": 532100.0, "volume medio": 722668.79}
{"stock": "WSON33", "date": "Jul 10, 2020", "open": 40.76, "high": 43.0, "low": 40.76, "close": 41.62, "volume": 13300.0, "volume medio": 9643.31}
{"stock": "PNVL3", "date": "Jul 10, 2020", "open": 31.0, "high": 31.67, "low": 30.9, "close": 30.87, "volume": 87000.0, "volume medio": 22867.87}
{"stock": "TOTS3", "date": "Jul 10, 2020", "open": 25.1, "high": 25.33, "low": 24.76, "close": 25.26, "volume": 1632400.0, "volume medio": 517150.25}
{"stock": "HAPV3", "date": "Jul 10, 2020", "open": 60.01, "high": 60.62, "low": 59.71, "close": 60.55, "volume": 1258100.0, "volume medio": 667620.6}
{"stock": "CCPR3", "date": "Jul 10, 2020", "open": 16.48, "high": 16.61, "low": 16.18, "close": 16.49, "volume": 48200.0, "volume medio": 23259.11}
{"stock": "ALPA3", "date": "Jul 10, 2020", "open": 25.01, "high": 25.01, "low": 24.95, "close": 24.95, "volume": 400.0, "volume medio": 239.41}
{"stock": "MOVI3", "date": "Jul 10, 2020", "open": 15.37, "high": 15.54, "low": 15.24, "close": 15.54, "volume": 1034000.0, "volume medio": 233489.29}
{"stock": "WEGE3", "date": "Jul 10, 2020", "open": 54.59, "high": 55.22, "low": 53.93, "close": 54.58, "volume": 2461600.0, "volume medio": 1074581.88}
{"stock": "LAME3", "date": "Jul 10, 2020", "open": 31.06, "high": 31.92, "low": 30.45, "close": 30.88, "volume": 1226600.0, "volume medio": 296856.67}
{"stock": "UGPA3", "date": "Jul 10, 2020", "open": 18.55, "high": 18.65, "low": 18.21, "close": 18.31, "volume": 2734600.0, "volume medio": 619484.77}
{"stock": "ALPA4", "date": "Jul 10, 2020", "open": 30.11, "high": 30.18, "low": 29.51, "close": 29.85, "volume": 553500.0, "volume medio": 241449.8}
{"stock": "LAME4", "date": "Jul 10, 2020", "open": 35.4, "high": 36.88, "low": 34.68, "close": 35.37, "volume": 7821000.0, "volume medio": 1799681.92}
{"stock": "RLOG3", "date": "Jul 10, 2020", "open": 20.24, "high": 20.47, "low": 20.18, "close": 20.35, "volume": 451300.0, "volume medio": 110694.17}
{"stock": "RAIL3", "date": "Jul 10, 2020", "open": 22.84, "high": 23.06, "low": 22.68, "close": 22.79, "volume": 3374900.0, "volume medio": 933147.62}
{"stock": "MTRE3", "date": "Jul 10, 2020", "open": 16.9, "high": 17.85, "low": 16.72, "close": 17.84, "volume": 1072400.0, "volume medio": 66838.31}
{"stock": "ALSO3", "date": "Jul 10, 2020", "open": 29.7, "high": 30.97, "low": 29.7, "close": 30.66, "volume": 1320100.0, "volume medio": 249806.47}
{"stock": "GNDI3", "date": "Jul 10, 2020", "open": 64.77, "high": 64.8, "low": 63.71, "close": 63.89, "volume": 750400.0, "volume medio": 1282490.59}
{"stock": "UNIP6", "date": "Jul 10, 2020", "open": 25.2, "high": 25.2, "low": 24.52, "close": 24.66, "volume": 62900.0, "volume medio": 19684.03}
{"stock": "GFSA3", "date": "Jul 10, 2020", "open": 6.32, "high": 6.46, "low": 6.2, "close": 6.42, "volume": 4046800.0, "volume medio": 329312.3}
{"stock": "UNIP5", "date": "Jul 10, 2020", "open": 28.3, "high": 28.3, "low": 28.3, "close": 28.3, "volume": 100.0, "volume medio": 182.95}
{"stock": "RDNI3", "date": "Jul 10, 2020", "open": 12.4, "high": 13.6, "low": 12.0, "close": 13.28, "volume": 70800.0, "volume medio": 1906.48}
{"stock": "UNIP3", "date": "Jul 10, 2020", "open": 29.95, "high": 29.95, "low": 29.45, "close": 29.45, "volume": 3700.0, "volume medio": 4042.83}
{"stock": "MRFG3", "date": "Jul 10, 2020", "open": 13.02, "high": 13.62, "low": 12.93, "close": 13.43, "volume": 7943300.0, "volume medio": 716305.75}
{"stock": "AALR3", "date": "Jul 10, 2020", "open": 11.43, "high": 11.43, "low": 11.08, "close": 11.23, "volume": 611700.0, "volume medio": 71365.8}
{"stock": "IDNT3", "date": "Jul 10, 2020", "open": 6.17, "high": 6.4, "low": 6.1, "close": 6.18, "volume": 202100.0, "volume medio": 11791.41}
{"stock": "MGLU3", "date": "Jul 10, 2020", "open": 79.29, "high": 80.99, "low": 78.95, "close": 80.44, "volume": 9245200.0, "volume medio": 4221292.72}
{"stock": "BIDI3", "date": "Jul 10, 2020", "open": 14.85, "high": 15.44, "low": 14.66, "close": 15.44, "volume": 307600.0, "volume medio": 37079.78}
{"stock": "BIDI4", "date": "Jul 10, 2020", "open": 15.96, "high": 16.82, "low": 15.8, "close": 16.81, "volume": 2784900.0, "volume medio": 172673.96}
{"stock": "STBP3", "date": "Jul 10, 2020", "open": 5.73, "high": 5.8, "low": 5.7, "close": 5.73, "volume": 1331900.0, "volume medio": 128348.95}
{"stock": "LINX3", "date": "Jul 10, 2020", "open": 27.0, "high": 27.0, "low": 26.3, "close": 26.8, "volume": 975300.0, "volume medio": 298462.49}
{"stock": "LWSA3", "date": "Jul 10, 2020", "open": 47.19, "high": 48.45, "low": 46.93, "close": 47.99, "volume": 922200.0, "volume medio": 293935.97}
{"stock": "VALE3", "date": "Jul 10, 2020", "open": 56.52, "high": 57.29, "low": 56.16, "close": 57.06, "volume": 9193600.0, "volume medio": 6355731.52}
{"stock": "BRAP3", "date": "Jul 10, 2020", "open": 33.49, "high": 34.24, "low": 33.49, "close": 34.2, "volume": 2700.0, "volume medio": 2347.8}
